wandering_in_gpt-0.0.0.data/scripts/wig
wndrng/__init__.py
wndrng/wandering.py
wndrng/i18n/__init__.py
wndrng/i18n/hints.py
wndrng/i18n/people.py
wndrng/i18n/prompts.py
wndrng/i18n/settings.py
wandering_in_gpt-0.0.0.dist-info/LICENSE
wandering_in_gpt-0.0.0.dist-info/METADATA
wandering_in_gpt-0.0.0.dist-info/WHEEL
wandering_in_gpt-0.0.0.dist-info/top_level.txt
wandering_in_gpt-0.0.0.dist-info/RECORD
