Metadata-Version: 2.1
Name: wandering-in-gpt
Version: 0.0.0
Summary: Wandering in GPT is a role-play game
Home-page: https://github.com/mountain/wandering-in-gpt
Author: Mingli Yuan
Author-email: mingli.yuan@gmail.com
Project-URL: Documentation, https://github.com/mountain/wandering-in-gpt
Project-URL: Source, https://github.com/mountain/wandering-in-gpt
Project-URL: Tracker, https://github.com/mountain/wandering-in-gpt/issues
Classifier: Programming Language :: Python :: 3
Classifier: License :: OSI Approved :: MIT License
Classifier: Operating System :: OS Independent
Requires-Python: >=3.6
License-File: LICENSE
Requires-Dist: requests
Requires-Dist: termcolor
